cd_sem/Panels.py
cd_sem/__init__.py
cd_sem/analysis.py
cd_sem/edges.py
cd_sem/fft.py
cd_sem/image.py
cd_sem/roughness.py
cd_sem/utils.py
cd_sem-0.1.2.dist-info/METADATA
cd_sem-0.1.2.dist-info/WHEEL
cd_sem-0.1.2.dist-info/licenses/LICENSE
cd_sem-0.1.2.dist-info/RECORD
