Metadata-Version: 2.4
Name: cd_sem
Version: 0.1.2
Summary: SEM image analysis
Author-email: Devin Grabner <devin.grabner@wsu.edu>, Harlan Heilman <harlan.heilman@wsu.edu>, Emma Vargo <evargo@lbl.gov>, Thomas Ferron <tjferron@lbl.gov>, Ricardo Ruiz <ricardo.ruiz@lbl.gov>
License-File: LICENSE
Requires-Python: >=3.12
Requires-Dist: jupyter
Requires-Dist: matplotlib
Requires-Dist: numpy
Requires-Dist: opencv-python
Requires-Dist: scikit-image
Requires-Dist: scipy
Requires-Dist: tifffile
Requires-Dist: tk
